fzflib/__init__.py
fzflib/__main__.py
fzflib/constants.py
fzflib/fzf.py
fzflib/logging.py
fzflib/utilities.py
fzflib-0.1.17.dist-info/LICENSE
fzflib-0.1.17.dist-info/METADATA
fzflib-0.1.17.dist-info/WHEEL
fzflib-0.1.17.dist-info/top_level.txt
fzflib-0.1.17.dist-info/RECORD
