Metadata-Version: 2.1
Name: fzflib
Version: 0.1.17
Summary: A Python library for interacting with FZF.
Home-page: https://github.com/AceofSpades5757/fzflib
Author: Kyle L. Davis
Author-email: AceofSpades5757.github@gmail.com
License: MIT
Project-URL: Documentation, https://fzflib.readthedocs.io/en/latest/
Project-URL: Author, https://github.com/AceofSpades5757
Classifier: Programming Language :: Python :: 3
Classifier: License :: OSI Approved :: MIT License
Classifier: Development Status :: 4 - Beta
Classifier: Operating System :: OS Independent
Classifier: Programming Language :: Python :: 3.6
Classifier: Programming Language :: Python :: 3.7
Classifier: Programming Language :: Python :: 3.8
Classifier: Programming Language :: Python :: 3.9
Classifier: Programming Language :: Python :: 3.10
Requires-Python: >=3.6
License-File: LICENSE
